recollex/__init__.py
recollex/abcs.py
recollex/bitmaps.py
recollex/engine.py
recollex/hooks.py
recollex/utils.py
recollex/encoder/__init__.py
recollex/encoder/splade.py
recollex/encoder/stonnx.py
recollex/io/__init__.py
recollex/io/segments.py
recollex/io/sqlite_store.py
recollex_gpu-0.1.8.dist-info/licenses/LICENSE
recollex_gpu-0.1.8.dist-info/METADATA
recollex_gpu-0.1.8.dist-info/WHEEL
recollex_gpu-0.1.8.dist-info/entry_points.txt
recollex_gpu-0.1.8.dist-info/top_level.txt
recollex_gpu-0.1.8.dist-info/RECORD
