Metadata-Version: 2.4
Name: recollex-gpu
Version: 0.1.8
Summary: RAG indexer based on Sparse Neural Embeddings.
Author-email: Chris Bates <1314008+chrsbats@users.noreply.github.com>
License-Expression: MIT
Classifier: Programming Language :: Python :: 3
Classifier: Programming Language :: Python :: 3 :: Only
Classifier: Programming Language :: Python :: 3.10
Classifier: Programming Language :: Python :: 3.11
Classifier: Programming Language :: Python :: 3.12
Classifier: Programming Language :: Python :: 3.13
Classifier: Operating System :: OS Independent
Requires-Python: >=3.10
License-File: LICENSE
Requires-Dist: python-ulid<4,>=3
Requires-Dist: pyroaring<2,>=1
Requires-Dist: huggingface_hub>=0.23
Requires-Dist: numpy>=2.0
Requires-Dist: scipy>=1.14
Requires-Dist: transformers<5,>=4.36
Provides-Extra: dev
Requires-Dist: pytest>=8.0.0; extra == "dev"
Requires-Dist: pytest-cov>=5.0.0; extra == "dev"
Provides-Extra: nlp
Requires-Dist: sentence-transformers[onnx]<6,>=5.1; (python_version < "3.13" and (sys_platform != "darwin" or platform_machine == "arm64")) and extra == "nlp"
Provides-Extra: cpu
Requires-Dist: onnxruntime>=1.17; extra == "cpu"
Provides-Extra: gpu
Requires-Dist: onnxruntime-gpu>=1.17; (sys_platform == "linux" or sys_platform == "win32") and extra == "gpu"
Provides-Extra: cuda
Requires-Dist: onnxruntime-gpu>=1.17; (sys_platform == "linux" or sys_platform == "win32") and extra == "cuda"
Provides-Extra: rocm
Requires-Dist: onnxruntime-rocm==1.22.2.post1; (sys_platform == "linux" and python_version == "3.10") and extra == "rocm"
Provides-Extra: directml
Requires-Dist: onnxruntime-directml>=1.17; sys_platform == "win32" and extra == "directml"
Provides-Extra: silicon
Requires-Dist: onnxruntime-silicon==1.16.3; (sys_platform == "darwin" and platform_machine == "arm64" and python_version < "3.12") and extra == "silicon"
Dynamic: license-file
